{
    "Ar36": {
        "error": 0.0002639844172280787,
        "error_type": "SEM",
        "filter_outliers_dict": {
            "filter_outliers": true,
            "iterations": 1,
            "std_devs": 3,
            "use_iqr_filtering": false,
            "use_standard_deviation_filtering": false
        },
        "fit": "parabolic",
        "fn": 280,
        "include_baseline_error": true,
        "n": 280,
        "outlier_excluded": [],
        "reviewed": true,
        "user_excluded": [],
        "value": 0.006978771493733419
    },
    "Ar37": {
        "error": 0.0038139271268312846,
        "error_type": "SEM",
        "filter_outliers_dict": {
            "filter_outliers": true,
            "iterations": 1,
            "std_devs": 3,
            "use_iqr_filtering": false,
            "use_standard_deviation_filtering": false
        },
        "fit": "linear",
        "fn": 280,
        "include_baseline_error": true,
        "n": 280,
        "outlier_excluded": [],
        "reviewed": true,
        "user_excluded": [],
        "value": -0.030269854780877514
    },
    "Ar38": {
        "error": 0.003229100700433727,
        "error_type": "SEM",
        "filter_outliers_dict": {
            "filter_outliers": true,
            "iterations": 1,
            "std_devs": 3,
            "use_iqr_filtering": false,
            "use_standard_deviation_filtering": false
        },
        "fit": "linear",
        "fn": 279,
        "include_baseline_error": true,
        "n": 280,
        "outlier_excluded": [
            191
        ],
        "reviewed": true,
        "user_excluded": [],
        "value": 0.0365546794899691
    },
    "Ar39": {
        "error": 0.01243657857719404,
        "error_type": "SEM",
        "filter_outliers_dict": {
            "filter_outliers": true,
            "iterations": 1,
            "std_devs": 3,
            "use_iqr_filtering": false,
            "use_standard_deviation_filtering": false
        },
        "fit": "parabolic",
        "fn": 279,
        "include_baseline_error": true,
        "n": 280,
        "outlier_excluded": [
            241
        ],
        "reviewed": true,
        "user_excluded": [],
        "value": 0.04481747784906235
    },
    "Ar40": {
        "error": 0.009712055680297269,
        "error_type": "SEM",
        "filter_outliers_dict": {
            "filter_outliers": true,
            "iterations": 1,
            "std_devs": 3,
            "use_iqr_filtering": false,
            "use_standard_deviation_filtering": false
        },
        "fit": "parabolic",
        "fn": 278,
        "include_baseline_error": true,
        "n": 280,
        "outlier_excluded": [
            88,
            157
        ],
        "reviewed": true,
        "user_excluded": [],
        "value": 1.6697263050807192
    },
    "Ar41": {
        "error": 0.03366675231742878,
        "error_type": "SEM",
        "filter_outliers_dict": {
            "filter_outliers": true,
            "iterations": 1,
            "std_devs": 2
        },
        "fit": "linear",
        "value": -0.263729736503828
    }
}